hue/README.md
hue/__init__.py
hue/__main__.py
hue/api/__init__.py
hue/api/bridge.py
hue/api/colors.py
hue/api/http.py
hue/api/light.py
hue/cli/__init__.py
hue/cli/bridge.py
hue/cli/console.py
hue/cli/light.py
hue/cli/main.py
hue_api-0.4.8.dist-info/entry_points.txt
hue_api-0.4.8.dist-info/LICENSE
hue_api-0.4.8.dist-info/WHEEL
hue_api-0.4.8.dist-info/METADATA
hue_api-0.4.8.dist-info/RECORD
